pygram11/__init__.py
pygram11/_backend.cpython-314t-x86_64-linux-musl.so
pygram11/_helpers.py
pygram11/_hist.py
pygram11/_misc.py
pygram11/_numpy.py
pygram11/config.py
pygram11/py.typed
pygram11.libs/libgcc_s-0cd532bd.so.1
pygram11.libs/libgomp-8949ffbe.so.1.0.0
pygram11.libs/libstdc++-5d72f927.so.6.0.33
pygram11-0.15.0.dist-info/METADATA
pygram11-0.15.0.dist-info/WHEEL
pygram11-0.15.0.dist-info/RECORD
pygram11-0.15.0.dist-info/licenses/LICENSE
