Metadata-Version: 2.2
Name: pygram11
Version: 0.15.0
Summary: Fast histogramming in Python built on pybind11 and OpenMP.
Author-Email: Doug Davis <ddavis@ddavis.io>
Maintainer-Email: Doug Davis <ddavis@ddavis.io>
Classifier: Programming Language :: C++
Classifier: Operating System :: Unix
Classifier: Operating System :: MacOS
Classifier: Operating System :: POSIX
Classifier: Operating System :: POSIX :: Linux
Classifier: Operating System :: Microsoft :: Windows
Classifier: License :: OSI Approved :: MIT License
Classifier: Intended Audience :: Science/Research
Classifier: Development Status :: 6 - Mature
Requires-Python: >=3.11
Requires-Dist: numpy
